pode/__init__.py
pode/hints.py
pode/pode.py
pode/utils.py
pode-0.4.3.dist-info/LICENSE
pode-0.4.3.dist-info/METADATA
pode-0.4.3.dist-info/WHEEL
pode-0.4.3.dist-info/RECORD
