Metadata-Version: 2.1
Name: pode
Version: 0.4.3
Summary: Implementation of an algorithm for a polygon decomposition by Hert, S. and Lumelsky, V., 1998
Author: GeorgySk
Author-email: skorobogatovgeorgy@gmail.com
Requires-Python: >=3.8,<4.0
Classifier: Programming Language :: Python :: 3
Classifier: Programming Language :: Python :: 3.8
Classifier: Programming Language :: Python :: 3.9
Classifier: Programming Language :: Python :: 3.10
Classifier: Programming Language :: Python :: 3.11
Classifier: Programming Language :: Python :: 3.12
Requires-Dist: gon (>=5.0.0,<6.0.0)
Requires-Dist: ground (>=8.1.0,<9.0.0)
Requires-Dist: networkx (>=2.8.8,<3.0.0)
Requires-Dist: sect (>=6.1.0,<7.0.0)
